parse_changelog/__init__.py
parse_changelog-1.0.8.data/scripts/parse-changelog
parse_changelog-1.0.8.dist-info/LICENSE
parse_changelog-1.0.8.dist-info/METADATA
parse_changelog-1.0.8.dist-info/WHEEL
parse_changelog-1.0.8.dist-info/top_level.txt
parse_changelog-1.0.8.dist-info/RECORD
