Metadata-Version: 2.1
Name: parse-changelog
Version: 1.0.8
Summary: A very simplistic changelog parser/updater
Home-page: https://github.com/cseelye/parse-changelog
Author: Carl Seelye
Author-email: cseelye@gmail.com
License: MIT
License-File: LICENSE
